finlab-1.5.6.dist-info/RECORD
finlab-1.5.6.dist-info/WHEEL
finlab-1.5.6.dist-info/entry_points.txt
finlab-1.5.6.dist-info/top_level.txt
finlab-1.5.6.dist-info/METADATA
finlab-1.5.6.dist-info/licenses/LICENSE
finlab/plot.py
finlab/config.py
finlab/market.py
finlab/dataframe.py
finlab/__init__.py
finlab/utils.py
finlab/ffn_core.py
finlab/backtest.py
finlab/tools/factor_analysis.py
finlab/tools/__init__.py
finlab/tools/event_study.py
finlab/core/mae_mfe.cpython-39-darwin.so
finlab/core/everything.js
finlab/core/utils_core.cpython-39-darwin.so
finlab/core/__init__.py
finlab/core/dashboard.py
finlab/core/metrics.cpython-39-darwin.so
finlab/core/backtest_core.cpython-39-darwin.so
finlab/core/style.css
finlab/core/report.cpython-39-darwin.so
finlab/core/aes.cpython-39-darwin.so
finlab/analysis/__init__.py
finlab/analysis/maeMfeAnalysis.py
finlab/analysis/liquidityAnalysis.py
finlab/analysis/inequalityAnalysis.py
finlab/analysis/alphaBetaAnalysis.py
finlab/analysis/drawdownAnalysis.py
finlab/analysis/periodStatsAnalysis.py
finlab/optimize/__init__.py
finlab/optimize/combinations.py
finlab/cli/portfolio_sync_manager.py
finlab/cli/__init__.py
finlab/cli/env.yml
finlab/cli/oauth_google.json
finlab/cli/cli.py
finlab/cli/utils.py
finlab/cli/data_encryptor.py
finlab/cli/schedule.py
finlab/cli/login.py
finlab/cli/workspace.py
finlab/cli/form_factory.py
finlab/cli/broker.py
finlab/cli/notebook.py
finlab/cli/install_conda.bat
finlab/cli/install_conda.sh
finlab/ml/qlib.py
finlab/ml/__init__.py
finlab/ml/feature.py
finlab/ml/cpcv.py
finlab/ml/utils.py
finlab/ml/label.py
finlab/ml/_qlib/config.py
finlab/ml/_qlib/log.py
finlab/ml/_qlib/__init__.py
finlab/ml/_qlib/typehint.py
finlab/ml/_qlib/constant.py
finlab/ml/_qlib/utils/time.py
finlab/ml/_qlib/utils/resam.py
finlab/ml/_qlib/utils/paral.py
finlab/ml/_qlib/utils/__init__.py
finlab/ml/_qlib/utils/index_data.py
finlab/ml/_qlib/utils/file.py
finlab/ml/_qlib/utils/serial.py
finlab/ml/_qlib/utils/exceptions.py
finlab/ml/_qlib/utils/objm.py
finlab/ml/_qlib/utils/mod.py
finlab/ml/_qlib/utils/data.py
finlab/ml/_qlib/contrib/__init__.py
