Metadata-Version: 2.4
Name: finlab
Version: 1.5.6
Summary: Analyzing stock has never been easier.
Author-email: FinLab <finlab.company@finlab.tw>
License: GPL-3.0-or-later
Project-URL: 文件教學, https://doc.finlab.tw/getting-start/
Project-URL: 選股策略, https://ai.finlab.tw/strategies/
Classifier: Programming Language :: Python :: 3.8
Classifier: Programming Language :: Python :: 3.9
Classifier: Programming Language :: Python :: 3.10
Classifier: Programming Language :: Python :: 3.11
Classifier: Programming Language :: Python :: 3.12
Classifier: Programming Language :: Python :: 3.13
Classifier: Programming Language :: Python :: 3.14
Classifier: License :: OSI Approved :: GNU General Public License v3 (GPLv3)
Classifier: Operating System :: OS Independent
Requires-Python: >=3.8
License-File: LICENSE
Requires-Dist: requests
Requires-Dist: numpy>=1.21.6
Requires-Dist: pandas>=1.5.3
Requires-Dist: pyarrow>=2.0.0
Requires-Dist: lz4
Requires-Dist: Cython
Requires-Dist: tqdm
Requires-Dist: jinja2
Requires-Dist: ipython
Provides-Extra: cli
Requires-Dist: pywebview; extra == "cli"
Requires-Dist: nbformat; extra == "cli"
Requires-Dist: google-auth-oauthlib; extra == "cli"
Requires-Dist: flask; extra == "cli"
Requires-Dist: cryptography>=43.0.0; extra == "cli"
Requires-Dist: rich_click>=1.8.3; extra == "cli"
Provides-Extra: qlib
Requires-Dist: pyyaml; extra == "qlib"
Requires-Dist: ruamel.yaml; extra == "qlib"
Requires-Dist: joblib; extra == "qlib"
Requires-Dist: redis; extra == "qlib"
Requires-Dist: python-redis-lock; extra == "qlib"
Requires-Dist: scipy; extra == "qlib"
Requires-Dist: dill; extra == "qlib"
Requires-Dist: matplotlib; extra == "qlib"
Requires-Dist: lightgbm; extra == "qlib"
Requires-Dist: xgboost; extra == "qlib"
Requires-Dist: catboost; extra == "qlib"
Requires-Dist: scikit-learn; extra == "qlib"
Requires-Dist: torch; extra == "qlib"
Requires-Dist: ta-lib; extra == "qlib"
Requires-Dist: plotly; extra == "qlib"
Dynamic: license-file
